MANIFEST.in
README.md
setup.py
AMQPLib/AMQPMsg.py
AMQPLib/__init__.py
robotframework_amqp.egg-info/PKG-INFO
robotframework_amqp.egg-info/SOURCES.txt
robotframework_amqp.egg-info/dependency_links.txt
robotframework_amqp.egg-info/not-zip-safe
robotframework_amqp.egg-info/requires.txt
robotframework_amqp.egg-info/top_level.txt