Metadata-Version: 1.1
Name: robotframework-amqp
Version: 0.0.2
Summary: AMQP library for usage in robotframework tests
Home-page: https://github.com/ctradu/robotframework-amqp
Author: Costin Radu
Author-email: UNKNOWN
License: MIT
Keywords: robotframework testing amqp
Platform: any
Classifier: Development Status :: 3 - Alpha
Classifier: Intended Audience :: Developers
Classifier: License :: OSI Approved :: MIT License
Classifier: Natural Language :: English
Classifier: Operating System :: OS Independent
Classifier: Programming Language :: Python :: 2
Classifier: Programming Language :: Python :: 2.7
Classifier: Topic :: Software Development :: Testing
